_bos_client_imp.cpython-38-x86_64-linux-gnu.so
bostorchconnector/__init__.py
bostorchconnector/_bos_bucket_iterable.py
bostorchconnector/_bos_bucket_key_data.py
bostorchconnector/_bos_dataset_common.py
bostorchconnector/_user_agent.py
bostorchconnector/_version.py
bostorchconnector/bos_checkpoint.py
bostorchconnector/bos_iterable_dataset.py
bostorchconnector/bos_map_dataset.py
bostorchconnector/bos_reader.py
bostorchconnector/bos_writer.py
bostorchconnector/_bos_client/__init__.py
bostorchconnector/_bos_client/_bos_client.py
bostorchconnector/_bos_client/bos_client_config.py
bostorchconnectorclient/__init__.py
bostorchconnectorclient/_bos_client_imp.pyi
bostorchconnectorclient/_logger_patch.py
bostorchconnectorclient/py.typed
bostorchconnector-1.0.0.dist-info/LICENSE
bostorchconnector-1.0.0.dist-info/METADATA
bostorchconnector-1.0.0.dist-info/WHEEL
bostorchconnector-1.0.0.dist-info/top_level.txt
bostorchconnector-1.0.0.dist-info/RECORD
