Metadata-Version: 2.1
Name: bostorchconnector
Version: 1.0.0
Summary: bostorchconnector, a Python package with a precompiled shared library
Author: 
Author-email: 
Classifier: Programming Language :: Python :: 3
Classifier: Operating System :: OS Independent
Requires-Python: >=3.8
License-File: LICENSE
